cardmarket_api/__init__.py
cardmarket_api/auth.py
cardmarket_api/cardmarket_api.py
cardmarket_api/clients/__init__.py
cardmarket_api/clients/base.py
cardmarket_api/clients/exceptions.py
cardmarket_api/clients/global_client.py
cardmarket_api/clients/marketplace_client.py
cardmarket_api/clients/product_client.py
cardmarket_api/clients/user_client.py
cardmarket_api-0.1.0.dist-info/AUTHORS.rst
cardmarket_api-0.1.0.dist-info/LICENSE
cardmarket_api-0.1.0.dist-info/METADATA
cardmarket_api-0.1.0.dist-info/WHEEL
cardmarket_api-0.1.0.dist-info/top_level.txt
cardmarket_api-0.1.0.dist-info/RECORD
