Metadata-Version: 2.1
Name: cardmarket-api
Version: 0.1.0
Summary: Python client for CardMarket API v3+
Home-page: https://github.com/SukiCZ/cardmarket_api
Author: Jakub Boukal
Author-email: www.bagr@gmail.com
License: MIT license
Keywords: cardmarket_api
Platform: UNKNOWN
Classifier: Development Status :: 2 - Pre-Alpha
Classifier: Intended Audience :: Developers
Classifier: License :: OSI Approved :: MIT License
Classifier: Natural Language :: English
Classifier: Programming Language :: Python :: 3
Classifier: Programming Language :: Python :: 3.6
Classifier: Programming Language :: Python :: 3.7
Classifier: Programming Language :: Python :: 3.8
Requires-Python: >=3.6
License-File: LICENSE
License-File: AUTHORS.rst
Requires-Dist: boto3 (>=1.21.3)
Requires-Dist: requests-oauthlib (>=1.3.1)
